setup.py
flask_response/__init__.py
flask_response.egg-info/PKG-INFO
flask_response.egg-info/SOURCES.txt
flask_response.egg-info/dependency_links.txt
flask_response.egg-info/requires.txt
flask_response.egg-info/top_level.txt