Metadata-Version: 1.0
Name: flask-response
Version: 0.0.3
Summary: egret, flask authentication used mongodb stored
Home-page: UNKNOWN
Author: UNKNOWN
Author-email: UNKNOWN
License: UNKNOWN
Platform: UNKNOWN
